MANIFEST.in
README.md
setup.cfg
setup.py
poco_ops/__init__.py
poco_ops/poco.py
poco_ops.egg-info/PKG-INFO
poco_ops.egg-info/SOURCES.txt
poco_ops.egg-info/dependency_links.txt
poco_ops.egg-info/entry_points.txt
poco_ops.egg-info/requires.txt
poco_ops.egg-info/top_level.txt
poco_ops/commands/__init__.py
poco_ops/commands/abstract_command.py
poco_ops/commands/build.py
poco_ops/commands/clean.py
poco_ops/commands/config.py
poco_ops/commands/init.py
poco_ops/commands/log.py
poco_ops/commands/pack.py
poco_ops/commands/plan.py
poco_ops/commands/project_init.py
poco_ops/commands/ps.py
poco_ops/commands/pull.py
poco_ops/commands/restart.py
poco_ops/commands/start.py
poco_ops/commands/stop.py
poco_ops/commands/unpack.py
poco_ops/resources/__init__.py
poco_ops/resources/command-hierarchy.yml
poco_ops/resources/docker-compose.yml
poco_ops/resources/poco.yml
poco_ops/services/__init__.py
poco_ops/services/abstract_repository.py
poco_ops/services/command_handler.py
poco_ops/services/command_runners.py
poco_ops/services/compose_handler.py
poco_ops/services/console_logger.py
poco_ops/services/environment_utils.py
poco_ops/services/file_repository.py
poco_ops/services/file_utils.py
poco_ops/services/package_handler.py
poco_ops/services/project_utils.py
poco_ops/services/state.py
poco_ops/services/state_utils.py
poco_ops/services/yaml_utils.py
poco_ops/tests/__init__.py
poco_ops/tests/abstract_test.py
poco_ops/tests/poco_test.py