Metadata-Version: 2.1
Name: poco-ops
Version: 1.0.3
Summary: poco lets you catalogue and manage your Docker projects using simple YAML files to shorten the route from finding your project to initialising it in your environment.
Home-page: https://www.shiwaforce.com
Author: Shiwaforce.com
License: Apache License 2.0
Platform: UNKNOWN
Classifier: Development Status :: 4 - Beta
Classifier: Intended Audience :: Developers
Classifier: Intended Audience :: System Administrators
Classifier: Natural Language :: English
Classifier: License :: OSI Approved :: Apache Software License
Classifier: Programming Language :: Python
Classifier: Programming Language :: Python :: 2.7
Classifier: Programming Language :: Python :: 3
Classifier: Programming Language :: Python :: 3.3
Classifier: Programming Language :: Python :: 3.4
Classifier: Programming Language :: Python :: 3.5
Classifier: Programming Language :: Python :: 3.6
